student_module/__init__.py
student_module/student.py
student_module-0.0.dist-info/METADATA
student_module-0.0.dist-info/WHEEL
student_module-0.0.dist-info/top_level.txt
student_module-0.0.dist-info/RECORD
