Metadata-Version: 2.1
Name: student-module
Version: 0.0
Summary: Student class with get_details, txtFile, db, and excel methods for storing data
Home-page: UNKNOWN
Author: Renuka
Author-email: renuka26092001@gmail.com
License: UNKNOWN
Platform: UNKNOWN
Requires-Python: >=3.6
Requires-Dist: openpyxl
Requires-Dist: mysql-connector-python
